{"users": [
{
  "localId": "F9CaKm7s1VYCsxWaXbWHajYesDy1",
  "email": "shahbazatalkah123@gmail.com",
  "emailVerified": true,
  "passwordHash": "IIrOa8HEdFep6QIMHw1/0tKRziYz7VLsAO0oh3oMn26bzs4+SPhD4d9kjhiJqmvSJ5VJwqeVmnmVAGsQJmSBrA==",
  "salt": "MfFpxY/98qZZrw==",
  "lastSignedInAt": "1776007493308",
  "createdAt": "1776001935055",
  "providerUserInfo": []
},
{
  "localId": "MuEymFxts4QWkiTL5MPGkw77vV93",
  "email": "zarifzahiri1998@gmail.com",
  "emailVerified": true,
  "passwordHash": "utXgLvPEeAGENxq1FQeV2DA4YyMdhFWCyoyhJWNPwyeHimiljftaXBFG9NVlNY07VNMXTkbJH6rrfYTjNZIL+w==",
  "salt": "ds/vHyEZMIkAwg==",
  "lastSignedInAt": "1776007457351",
  "createdAt": "1776002036506",
  "providerUserInfo": []
}]}